[
  {
    "startTime": 166,
    "endTime": 1209,
    "duration": 1043,
    "text": "Use all of that."
  },
  {
    "startTime": 1209,
    "endTime": 2377,
    "duration": 1168,
    "text": "Use that entire..."
  },
  {
    "startTime": 2919,
    "endTime": 4963,
    "duration": 2044,
    "text": "Don't edit any of my answer."
  },
  {
    "startTime": 5422,
    "endTime": 6423,
    "duration": 1001,
    "text": "Put it online."
  },
  {
    "startTime": 6423,
    "endTime": 7757,
    "duration": 1334,
    "text": "Let the people know."
  },
  {
    "startTime": 12053,
    "endTime": 13221,
    "duration": 1168,
    "text": "Accidentally?"
  },
  {
    "startTime": 13221,
    "endTime": 15640,
    "duration": 2419,
    "text": "I definitely stole a pair of vintage Levi's"
  },
  {
    "startTime": 15640,
    "endTime": 17726,
    "duration": 2086,
    "text": "from my best friend in high school."
  },
  {
    "startTime": 17726,
    "endTime": 19144,
    "duration": 1418,
    "text": "I grew up in Japan."
  },
  {
    "startTime": 19310,
    "endTime": 21062,
    "duration": 1752,
    "text": "Japanese people have such cute little things"
  },
  {
    "startTime": 21062,
    "endTime": 22230,
    "duration": 1168,
    "text": "and I think that we just..."
  },
  {
    "startTime": 22814,
    "endTime": 23982,
    "duration": 1168,
    "text": "Couldn't help ourselves."
  },
  {
    "startTime": 24441,
    "endTime": 25275,
    "duration": 834,
    "text": "I blame my mom."
  },
  {
    "startTime": 28778,
    "endTime": 29529,
    "duration": 751,
    "text": "Olivia."
  },
  {
    "startTime": 29529,
    "endTime": 30447,
    "duration": 918,
    "text": "Amanda Peet."
  },
  {
    "startTime": 30447,
    "endTime": 31990,
    "duration": 1543,
    "text": "She's got great taste."
  },
  {
    "startTime": 31990,
    "endTime": 34075,
    "duration": 2085,
    "text": "I would steal from her and not even feel bad."
  },
  {
    "startTime": 35535,
    "endTime": 36536,
    "duration": 1001,
    "text": "Sarah Paulson."
  },
  {
    "startTime": 38872,
    "endTime": 40540,
    "duration": 1668,
    "text": "Well Harrison Ford is my neighbor."
  },
  {
    "startTime": 40540,
    "endTime": 42459,
    "duration": 1919,
    "text": "It's— it's Indy."
  },
  {
    "startTime": 42459,
    "endTime": 44711,
    "duration": 2252,
    "text": "It's— Indiana Jones is my neighbor."
  },
  {
    "startTime": 47422,
    "endTime": 48840,
    "duration": 1418,
    "text": "I think I'm going to answer Amanda"
  },
  {
    "startTime": 48840,
    "endTime": 50383,
    "duration": 1543,
    "text": "for almost all of these answers "
  },
  {
    "startTime": 50383,
    "endTime": 51801,
    "duration": 1418,
    "text": "'cause I love her that much."
  },
  {
    "startTime": 53636,
    "endTime": 54345,
    "duration": 709,
    "text": "Olivia."
  },
  {
    "startTime": 54345,
    "endTime": 55263,
    "duration": 918,
    "text": "Amanda."
  },
  {
    "startTime": 55263,
    "endTime": 56431,
    "duration": 1168,
    "text": "Oh my God, "
  },
  {
    "startTime": 56431,
    "endTime": 58016,
    "duration": 1585,
    "text": "what if Amanda doesn't say me?"
  },
  {
    "startTime": 60810,
    "endTime": 61895,
    "duration": 1085,
    "text": "Does she say me?"
  },
  {
    "startTime": 61895,
    "endTime": 62937,
    "duration": 1042,
    "text": "I want to see her answer."
  },
  {
    "startTime": 68193,
    "endTime": 69194,
    "duration": 1001,
    "text": "That just really depends."
  },
  {
    "startTime": 69194,
    "endTime": 71196,
    "duration": 2002,
    "text": "When my kids steal my jeans I notice."
  },
  {
    "startTime": 71196,
    "endTime": 73198,
    "duration": 2002,
    "text": "A friend of mine has stolen from me, "
  },
  {
    "startTime": 73198,
    "endTime": 74908,
    "duration": 1710,
    "text": "although she considers it"
  },
  {
    "startTime": 74908,
    "endTime": 76326,
    "duration": 1418,
    "text": "borrowing for a long time."
  },
  {
    "startTime": 76326,
    "endTime": 78703,
    "duration": 2377,
    "text": "It'll be things that are annoying too like my"
  },
  {
    "startTime": 78703,
    "endTime": 79829,
    "duration": 1126,
    "text": "iPhone charger."
  },
  {
    "startTime": 79829,
    "endTime": 81081,
    "duration": 1252,
    "text": "You're like that's something— I mean"
  },
  {
    "startTime": 81081,
    "endTime": 83666,
    "duration": 2585,
    "text": "take my earrings over my iPhone charger."
  },
  {
    "startTime": 86920,
    "endTime": 87921,
    "duration": 1001,
    "text": "A Birkin bag."
  },
  {
    "startTime": 88505,
    "endTime": 89881,
    "duration": 1376,
    "text": "Did I say that quickly enough?"
  },
  {
    "startTime": 89881,
    "endTime": 90840,
    "duration": 959,
    "text": "A car."
  },
  {
    "startTime": 90840,
    "endTime": 93384,
    "duration": 2544,
    "text": "That just makes good financial sense."
  },
  {
    "startTime": 93384,
    "endTime": 95136,
    "duration": 1752,
    "text": "If you could steal one item from the show—"
  },
  {
    "startTime": 95136,
    "endTime": 95970,
    "duration": 834,
    "text": "No."
  },
  {
    "startTime": 96471,
    "endTime": 97555,
    "duration": 1084,
    "text": "I don't care about"
  }
]