{
  "videoId": "C-GrRIgdmW8",
  "title": "Herbie Hancock: No Such Thing as a Wrong Note | MasterClass Moments | MasterClass",
  "languageCode": "en-us",
  "autoCaptionsCount": 17,
  "manualCaptionsCount": 16,
  "autoCaptionsText": "in the middle of one of the songs during miles of solo I played this chord that was so wrong I thought I had just destroyed everything and reduced that great night to rubble miles took a breath and he played some notes and he made my chord right and I could not figure out how he did that it sounded like magic you know it took me years to figure out what actually happened here's what happened I judged what I had played miles didn't miles just accepted it as something new that happened and he did what any jazz musicians should always try to do and that is try to make anything that happens into something of value",
  "manualCaptionsText": "In the middle of one of the\nsongs, during Miles' solo, I played this chord that was\nso wrong I thought I had just destroyed everything, and\nreduced that great night to rubble. Miles took a breath, and\nhe played some notes. And he made my chord right. And I could not figure\nout how he did that. It sounded like magic, you know? It took me years to figure\nout what actually happened. Here's what happened. I judged what I had played. Miles didn't. Miles just accepted it as\nsomething new that happened. And he did what any jazz\nmusician should always try to do, and that is try\nto make anything that happens into something of value."
}